triton_requests/__init__.py
triton_requests-0.0.3.dist-info/METADATA
triton_requests-0.0.3.dist-info/WHEEL
triton_requests-0.0.3.dist-info/licenses/LICENSE
triton_requests-0.0.3.dist-info/RECORD
