Metadata-Version: 2.1
Name: triton_requests
Version: 0.0.3
Summary: A high level package for Nvidia Triton requests
Project-URL: Homepage, https://github.com/scampion/triton_requests
Project-URL: Bug Tracker, https://github.com/scampion/triton_requests/issues
Author-email: Sebastien Campion <sebastien.campion@foss4.eu>
License-File: LICENSE
Classifier: License :: OSI Approved :: MIT License
Classifier: Operating System :: OS Independent
Classifier: Programming Language :: Python :: 3
Requires-Python: >=3.7
Requires-Dist: numpy
Requires-Dist: tritonclient[http]
